madap_cli.py
madap_gui.py
figures_creation/__init__.py
figures_creation/test_joblib.py
madap/__init__.py
madap/madap_cli.py
madap/madap_gui.py
madap/data_acquisition/__init__.py
madap/data_acquisition/data_acquisition.py
madap/echem/__init__.py
madap/echem/procedure.py
madap/echem/arrhenius/__init__.py
madap/echem/arrhenius/arrhenius.py
madap/echem/arrhenius/arrhenius_plotting.py
madap/echem/e_impedance/__init__.py
madap/echem/e_impedance/e_impedance.py
madap/echem/e_impedance/e_impedance_plotting.py
madap/echem/voltammetry/__init__.py
madap/echem/voltammetry/voltammetry.py
madap/echem/voltammetry/voltammetry_CA.py
madap/echem/voltammetry/voltammetry_CP.py
madap/echem/voltammetry/voltammetry_CV.py
madap/echem/voltammetry/voltammetry_plotting.py
madap/logger/__init__.py
madap/logger/logger.py
madap/plotting/__init__.py
madap/plotting/plotting.py
madap/plotting/styles/nature.mplstyle
madap/plotting/styles/no-latex.mplstyle
madap/plotting/styles/science.mplstyle
madap/utils/__init__.py
madap/utils/gui_elements.py
madap/utils/suggested_circuits.py
madap/utils/utils.py
src/__init__.py
src/madap_cli.py
src/madap_gui.py
src/madap/__init__.py
src/madap/data_acquisition/__init__.py
src/madap/data_acquisition/data_acquisition.py
src/madap/echem/__init__.py
src/madap/echem/procedure.py
src/madap/echem/arrhenius/__init__.py
src/madap/echem/arrhenius/arrhenius.py
src/madap/echem/arrhenius/arrhenius_plotting.py
src/madap/echem/e_impedance/__init__.py
src/madap/echem/e_impedance/e_impedance.py
src/madap/echem/e_impedance/e_impedance_plotting.py
src/madap/echem/voltammetry/__init__.py
src/madap/echem/voltammetry/voltammetry.py
src/madap/echem/voltammetry/voltammetry_CA.py
src/madap/echem/voltammetry/voltammetry_CP.py
src/madap/echem/voltammetry/voltammetry_CV.py
src/madap/echem/voltammetry/voltammetry_plotting.py
src/madap/logger/__init__.py
src/madap/logger/logger.py
src/madap/plotting/__init__.py
src/madap/plotting/plotting.py
src/madap/plotting/styles/nature.mplstyle
MADAP-1.2.8.dist-info/AUTHORS.rst
MADAP-1.2.8.dist-info/LICENSE
MADAP-1.2.8.dist-info/METADATA
MADAP-1.2.8.dist-info/WHEEL
MADAP-1.2.8.dist-info/entry_points.txt
MADAP-1.2.8.dist-info/top_level.txt
MADAP-1.2.8.dist-info/RECORD
