Metadata-Version: 2.2
Name: MADAP
Version: 1.2.8
Summary: This is MADAP, a software package for the analysis of electrochemical data.
Home-page: https://github.com/fuzhanrahmanian/MADAP
Author: Fuzhan Rahmanian
Author-email: fuzhanrahmanian@gmail.com
License: MIT license
Keywords: madap
Classifier: Development Status :: 3 - Alpha
Classifier: Intended Audience :: Developers
Classifier: Intended Audience :: Science/Research
Classifier: License :: OSI Approved :: MIT License
Classifier: Natural Language :: English
Classifier: Operating System :: OS Independent
Classifier: Programming Language :: Python :: 3
Classifier: Programming Language :: Python :: 3.8
Classifier: Programming Language :: Python :: 3.9
Classifier: Programming Language :: Python :: 3.10
Classifier: Topic :: Scientific/Engineering :: Chemistry
Classifier: Topic :: Scientific/Engineering :: Physics
Classifier: Topic :: Scientific/Engineering :: Visualization
Requires-Python: >=3.8
License-File: LICENSE
License-File: AUTHORS.rst
Requires-Dist: attrs==21.4.0
Requires-Dist: matplotlib
Requires-Dist: numpy
Requires-Dist: pandas
Requires-Dist: PySimpleGUI
Requires-Dist: pytest
Requires-Dist: scikit_learn
Requires-Dist: ruptures
Requires-Dist: impedance==1.4.1
Provides-Extra: dev
Requires-Dist: pytest>=3; extra == "dev"
Dynamic: author
Dynamic: author-email
Dynamic: classifier
Dynamic: description
Dynamic: home-page
Dynamic: keywords
Dynamic: license
Dynamic: provides-extra
Dynamic: requires-dist
Dynamic: requires-python
Dynamic: summary
